config/__init__.py
config/parser.py
config/tokens.py
config-0.5.1.dist-info/LICENSE
config-0.5.1.dist-info/METADATA
config-0.5.1.dist-info/WHEEL
config-0.5.1.dist-info/top_level.txt
config-0.5.1.dist-info/RECORD
